alphabet/__init__.py
alphabet/alphabet.py
alphabet/tests/__init__.py
alphabet/tests/test_alphabet.py
alphabet-0.0.8.dist-info/LICENSE.txt
alphabet-0.0.8.dist-info/METADATA
alphabet-0.0.8.dist-info/WHEEL
alphabet-0.0.8.dist-info/top_level.txt
alphabet-0.0.8.dist-info/RECORD
