Metadata-Version: 1.0
Name: alphabet
Version: 0.0.8
Summary: Uses various methods to recognize text
Home-page: https://github.com/reale/alphabet
Author: Roberto Reale
Author-email: roberto@reale.me
License: UNKNOWN
Platform: UNKNOWN
